RISC_SPM/src/RISC_SPM.v
module RISC_SPM #(parameter word_size=8, sel1_size=3, sel2_size=2) 
		(input clk, rst);
		
		//Data Nets
		wire [sel1_size-1: 0] sel_bus_1_mux;
		wire [sel2_size-1: 0] Sel_bus_2_mux;
		wire zero;
		wire [word_size-1: 0] instruction, address, bus_1, mem_word;
		
		//Control Nets
		wire load_R0, load_R1, load_R2, load_R3, load_PC, inc_PC, load_IR,
		     load_add_R, load_Reg_Y, load_Reg_Z, write;
		
		Processing_Unit M0_Processor (instruction, address, bus_1, zero, mem_word,
						load_R0, load_R1, load_R2, load_R3, load_PC, 
						inc_PC, sel_bus_1_mux, Sel_bus_2_mux, load_IR,
						load_add_R, load_Reg_Y, load_Reg_Z, clk, rst);
		
		Control_Unit M1_Controller (Sel_bus_2_mux, sel_bus_1_mux, load_R0, load_R1,
						load_R2, load_R3, load_PC, inc_PC, load_IR, 
						load_add_R, load_Reg_Y, load_Reg_Z, write, 
						instruction, zero, clk, rst);
		
		Memory_Unit M2_MEM (
				    .data_out(mem_word),
				    .data_in(bus_1),
				    .address(address),
				    .clk(clk),
				    .write(write));
endmodule



module Processing_Unit #(parameter word_size=8, op_size=4, sel1_size=3, sel2_size=2)
	(output [word_size-1: 0] instruction, address, bus_1,
	 output zflag,
	 input [word_size-1: 0] mem_word,
	 input load_R0, load_R1, load_R2, load_R3, load_PC, inc_PC,
	 input [sel1_size-1: 0] sel_bus_1_mux,
	 input [sel2_size-1: 0] sel_bus_2_mux,
	 input load_IR, load_add_R, load_Reg_Y, load_Reg_Z, 
	 input clk, rst);
	
	wire [word_size-1: 0] bus_2;
	wire [word_size-1: 0] R0_out, R1_out, R2_out, R3_out;
	wire [word_size-1: 0] PC_count, Y_value, alu_out;
	wire alu_zero_flag;
	wire [op_size-1: 0] opcode = instruction [word_size-1: word_size-op_size];
	
	Register_Unit        R0    (R0_out, bus_2, load_R0, clk, rst);
	Register_Unit        R1    (R1_out, bus_2, load_R1, clk, rst);
	Register_Unit        R2    (R2_out, bus_2, load_R2, clk, rst);
	Register_Unit        R3    (R3_out, bus_2, load_R3, clk, rst);
	Register_Unit        Reg_Y (Y_value, bus_2, load_Reg_Y, clk, rst);
	D_flop               Reg_Z (zflag, alu_zero_flag, load_Reg_Z, clk, rst);
	Address_Register     Add_R (address, bus_2, load_add_R, clk, rst);
	Instruction_Register IR    (instruction, bus_2, load_IR, clk, rst);
	Program_Counter      PC    (PC_count, bus_2, load_pc, inc_pc, clk, rst);
	Multiplexer_5ch      Mux_1 (bus_1, R0_out, R1_out, R2_out, R3_out, PC_count,
				     sel_bus_1_mux);
	Multiplexer_3ch      Mux_2 (bus_2, alu_out, bus_1, mem_word, sel_bus_2_mux);
	Alu_RISC             ALU   (alu_out, alu_zero_flag, Y_value, bus_1, opcode);
endmodule



module Register_Unit #(parameter word_size = 8)
	(output reg [word_size-1: 0] data_out,
	 input [word_size-1: 0] data_in,
	 input load, clk, rst);
	
	always @ (posedge clk, negedge rst)
	   if (rst == 1'b0) data_out <= 0;
	   else if (load) data_out <= data_in;
endmodule



module D_flop (output reg data_out,
		input data_in, load, clk, rst);
	
	always @ (posedge clk, negedge rst)
	   if (rst == 1'b0) data_out <= 0;
	   else if (load == 1'b1) data_out <= data_in;
endmodule



module Address_Register #(parameter word_size=8)
	(output reg [word_size-1: 0] data_out,
	 input [word_size-1: 0] data_in,
	 input load, clk, rst);
	
	always @ (posedge clk, negedge rst)
	   if (rst == 1'b0) data_out <= 0;
	   else if (load == 1'b1) data_out <= data_in;
endmodule 



module Instruction_Register #(parameter word_size=8)
	(output reg [word_size-1: 0] data_out,
	 input [word_size-1: 0] data_in,
	 input load, clk, rst);
	
	always @ (posedge clk, negedge rst)
	   if (rst == 1'b0) data_out <= 0;
	   else if (load == 1'b1) data_out <= data_in;
endmodule



module Program_Counter #(parameter word_size=8)
	(output reg [word_size-1: 0] count,
	 input [word_size-1: 0] data_in,
	 input load_PC, inc_PC,
	 input clk, rst);
	
	always @ (posedge clk, negedge rst)
	   if (rst == 1'b0) count <= 0;
	   else if (load_PC == 1'b0) count <= data_in;
	   else if (inc_PC == 1'b1) count <= count +1;
endmodule 



module Multiplexer_5ch #(parameter word_size=8)
	(output [word_size-1: 0] mux_out,
	 input [word_size-1: 0] data_a, data_b, data_c, data_d, data_e,
	 input [2: 0] sel);
	 
	 assign mux_out = (sel == 0) ? data_a : (sel == 1)
	 			      ? data_b : (sel == 2)
	 			      ? data_c : (sel == 3)
	 			      ? data_d : (sel == 4)
	 			      ? data_e : 'bx; 
endmodule



module Multiplexer_3ch #(parameter word_size=8)
	(output [word_size-1: 0] mux_out,
	 input [word_size-1: 0] data_a, data_b, data_c,
	 input [1: 0] sel);
	
	assign mux_out = (sel == 0) ? data_a : (sel == 1)
				     ? data_b : (sel == 2)
	 			     ? data_c : 'bx;
endmodule

module Alu_RISC #(parameter word_size=8, op_size=4,
	//Opcodes
	NOP = 4'b0000,
	ADD = 4'b0001,
	SUB = 4'b0010,
	AND = 4'b0011,
	NOT = 4'b0100,
	RD  = 4'b0101 ,
	WR  = 4'b0110,
	BR  = 4'b0111 ,
	BRZ = 4'b1000)
	//Ports
	(output reg [word_size-1: 0] alu_out,
	 output alu_zero_flag,
	 input [word_size-1: 0] data_1, data_2,
	 input [op_size-1: 0] sel);
	
	assign alu_zero_flag = ~|alu_out;	//unsure if NOR
	always @(sel, data_1, data_2)
	   case (sel)
	   	 NOP: alu_out = 0;
	   	 ADD: alu_out = data_1 + data_2; // Reg_Y + Bus_1
	   	 SUB: alu_out = data_2 - data_1;
	   	 AND: alu_out = data_1 & data_2;
	   	 NOT: alu_out = ~data_2;
	   	 default: alu_out = 0;
	   endcase
endmodule



module Control_Unit #(parameter word_size=8, op_size=4, state_size=4,
		       src_size=2, dest_size=2, sel1_size=3, sel2_size=2)
	(output [sel2_size-1: 0] sel_bus_2_mux,
	 output [sel1_size-1: 0] sel_bus_1_mux,
	 output reg load_R0, load_R1, load_R2, load_R3,load_PC, inc_PC,
	            load_IR, load_add_R, load_Reg_Y, load_Reg_Z, write,
	 input [word_size-1: 0] instruction,
	 input zero, clk, rst);
	
	//State Codes
	  parameter s_idle=0, s_fet1=1, s_fet2=2, s_dec=3, s_ex1=4, s_rd1=5,
	            s_rd2=6, s_wr1=7, s_wr2=8, s_br1=9, s_br2=10, s_halt=11;
	
	//Opcodes
	  parameter NOP=0, ADD=1, SUB=2, AND=3, NOT=4, RD=5, WR=6, BR=7, BRZ=8;
	
	//Source and Destination Codes
	  parameter R0=0, R1=1, R2=2, R3=3;
	  
	  reg [state_size-1: 0] state, next_state;
	  reg sel_ALU, sel_bus_1, sel_mem;
	  reg sel_R0, sel_R1, sel_R2, sel_R3, sel_PC;
	  reg err_flag;
	  wire [op_size-1: 0] opcode = instruction [word_size-1: word_size - op_size];
	  wire [src_size-1: 0] src = instruction [src_size + dest_size -1: dest_size];
	  wire [dest_size-1: 0] dest = instruction [dest_size-1: 0];
	  
	//Mux selectors
	  assign sel_bus_1_mux[sel1_size-1: 0] = sel_R0 ? 0:
	  					   sel_R1 ? 1:
	  					   sel_R2 ? 2:
	  					   sel_R3 ? 3:
	  					   sel_PC ? 4: 3'bx; // 3-bits, sized number
	  
	  always @(posedge clk, negedge rst) begin: state_transitions
	     if (rst == 0) state <= s_idle; 
	     else state <= next_state; 
	     end 
	 
	 always @ (state, opcode, src, dest, zero) begin: output_and_next_state
	    sel_R0=0; sel_R1=0; sel_R2=0; sel_R3=0; sel_PC=0;
	    load_R0=0; load_R1=0; load_R2=0; load_R3=0; load_PC=0;
	    load_IR=0; load_add_R=0; load_Reg_Y=0; load_Reg_Z=0;
	    inc_PC=0;
	    sel_bus_1=0;
	    sel_ALU=0;
	    sel_mem=0;
	    write=0;
	    err_flag=0;  //Used for de-bug in simulation
	    next_state=state;
	       case (state)   s_idle: next_state = s_fet1;
	                      s_fet1: begin
	                                next_state = s_fet2;
	                                sel_PC = 1;
	                                sel_bus_1 = 1;
	                                load_add_R = 1;
	                              end
	                      s_fet2: begin
	                                next_state = s_dec;
	                                sel_mem = 1;
	                                load_IR = 1;
	                                inc_PC = 1;
	                              end
	                      s_dec:   case (opcode)
	                                   NOP: next_state = s_fet1;
	                                   ADD, SUB, AND: begin
	                                      next_state = s_ex1;
	                                      sel_bus_1 = 1;
	                                      load_Reg_Y = 1;
	                                      case (src)
	                                           R0: sel_R0 = 1;
	                                           R1: sel_R1 = 1;
	                                           R2: sel_R2 = 1;
	                                           R3: sel_R3 = 1;
	                                           default: err_flag = 1;
	                                      endcase
	                                      end //ADD, SUB, AND
	                                   NOT: begin
	                                        next_state = s_fet1;
	                                        load_Reg_Z = 1;
	                                        sel_ALU = 1;
	                                        case (src)
	                                           R0: sel_R0 = 1;
	                                           R1: sel_R1 = 1;
	                                           R2: sel_R2 = 1;
	                                           R3: sel_R3 = 1;
	                                           default: err_flag = 1;
	                                        endcase
	                                        case (dest)
	                                           R0: load_R0 = 1;
	                                           R1: load_R1 = 1;
	                                           R2: load_R2 = 1;
	                                           R3: load_R3 = 1;
	                                           default: err_flag = 1;
	                                        endcase
	                                        end //NOT
	                                   RD: begin    
	                                       next_state = s_rd1;
	                                       sel_PC = 1; sel_bus_1 = 1; load_add_R = 1;
	                                       end //RD
	                                   WR: begin
	                                       next_state = s_wr1;
	                                       sel_PC = 1; sel_bus_1 = 1; load_add_R = 1;
	                                       end //WR
	                                   BR: begin
	                                       next_state = s_br1;
	                                       sel_PC = 1; sel_bus_1 = 1; load_add_R = 1;
	                                       end //WR
	                                   BRZ: if (zero == 1) begin
	                                        next_state = s_br1;
	                                        sel_PC = 1; sel_bus_1 = 1; load_add_R = 1;
	                                        end //BRZ
	                                   else begin
	                                        next_state = s_fet1;
	                                        inc_PC = 1;
	                                        end
	                                   default: next_state = s_halt;
	                              endcase //(opcode)
	                    s_ex1:    begin
	                              next_state = s_fet1;
	                              load_Reg_Z = 1;
	                              sel_ALU = 1;
	                              case (dest)
	                                   R0: begin sel_R0 = 1; load_R0 = 1; end
	                                   R1: begin sel_R1 = 1; load_R1 = 1; end
	                                   R2: begin sel_R2 = 1; load_R2 = 1; end
	                                   R3: begin sel_R3 = 1; load_R3 = 1; end
	                                   default: err_flag = 1;
	                              endcase
	                              end
	                    s_rd1:    begin
	                              next_state = s_rd2;
	                              sel_mem = 1;
	                              load_add_R = 1;
	                              inc_PC = 1;
	                              end
	                    s_wr1:    begin
	                              next_state = s_wr2;
	                              sel_mem = 1;
	                              load_add_R = 1;
	                              inc_PC = 1;
	                              end
	                    s_rd2:    begin
	                              next_state = s_fet1;
	                              sel_mem = 1;
	                              case (dest)
	                                   R0: load_R0 = 1;
	                                   R1: load_R1 = 1;
	                                   R2: load_R2 = 1;
	                                   R3: load_R3 = 1;
	                                   default: err_flag = 1;
	                              endcase
	                              end
	                    s_wr2:    begin
	                              next_state = s_fet1;
	                              write = 1;
	                              case (src)
	                                   R0: sel_R0 = 1;
	                                   R1: sel_R1 = 1;
	                                   R2: sel_R2 = 1;
	                                   R3: sel_R3 = 1;
	                                   default: err_flag = 1;
	                              endcase
	                              end
	                    s_br1:    begin
	                              next_state = s_br2; sel_mem = 1;
	                              load_add_R = 1;
	                              end
	                    s_br2:    begin
	                              next_state = s_fet1; sel_mem = 1;
	                              load_PC = 1;
	                              end
	                    s_halt:   next_state = s_halt;
	                    default:  next_state = s_idle;
	       endcase
	    end
endmodule



module Memory_Unit #(parameter word_size=8, memory_size=256)
       (output [word_size-1: 0] data_out,
        input [word_size-1: 0] data_in,
        input [word_size-1: 0] address,
        input clk, write);
        
        reg [word_size-1: 0] memory [memory_size-1: 0];
        
        assign data_out = memory[address];
        always @(posedge clk)
           if (write) memory[address] <= data_in;
endmodule

RISC_SPM/test/tb_RISC_SPM.v
`timescale 1ns/1ps

module tb_RISC_SPM;
	parameter word_size = 8;
	reg rst;
	wire clk;
        reg [8: 0] k;
        
        Clock_Unit M1 (clk);
        RISC_SPM M2 (clk, rst);
        
        
        // define probes
           wire [word_size-1: 0] wordO, word1, word2, word3, word4, word5, word6,
                                 word7, word8, word9, word10, word11 , word12, word13,
                                 word14, word128, word129, word130, word131, word132,
                                 word133, word134, word135, word136, word137, word255,
                                 word138, word139, word140;
                                 
           assign word0 = M2.M2_MEM.memory[0],
                  word1 = M2.M2_MEM.memory[1],
                  word2 = M2.M2_MEM.memory[2],
                  word3 = M2.M2_MEM.memory[3],
                  
                  word4 = M2.M2_MEM.memory[4],
                  word5 = M2.M2_MEM.memory[5],
                  word6 = M2.M2_MEM.memory[6],
                  word7 = M2.M2_MEM.memory[7],
                  word8 = M2.M2_MEM.memory[8],
                  word9 = M2.M2_MEM.memory[9],
                  word10 = M2.M2_MEM.memory[10],
                  word11 = M2.M2_MEM.memory[11],
                  word12 = M2.M2_MEM.memory[12],
                  word13 = M2.M2_MEM.memory[13],
                  word14 = M2.M2_MEM.memory[14],
                  
                  word128 = M2.M2_MEM.memory[128],
                  word129 = M2.M2_MEM.memory[129],
                  word130 = M2.M2_MEM.memory[130],
                  word131 = M2.M2_MEM.memory[131],
                  word132 = M2.M2_MEM.memory[132],
                  word133 = M2.M2_MEM.memory[133],
                  word134 = M2.M2_MEM.memory[134],
                  word135 = M2.M2_MEM.memory[135],
                  word136 = M2.M2_MEM.memory[136],
                  word137 = M2.M2_MEM.memory[137],
                  word138 = M2.M2_MEM.memory[138],
                  word139 = M2.M2_MEM.memory[139],
                  word140 = M2.M2_MEM.memory[140],
                  word255 = M2.M2_MEM.memory[255];
           //initial #2800 $finish;
           //RISC_SPM module1();
           initial 
               begin
               $dumpfile("tb_RISC_SPM.vcd");
               $dumpvars(0, tb_RISC_SPM);
               #2800 $finish;
               end
        
        // Flush Memory
           initial begin: Flush_Memory 
           #2 rst=0; for (k=0; k<=255; k=k+1) M2.M2_MEM.memory[k]=0; #10 rst=1;
           end
           
           initial begin: Load_program
           #5
                                                      // opcode_src_dest
            M2.M2_MEM.memory[0] = 8'b0000_00_00;      // NOP
            M2.M2_MEM.memory[1] = 8'b0101_00_10;	// Read 130 to R2
            M2.M2_MEM.memory[2] = 130;
            M2.M2_MEM.memory[3] = 8'b0101_00_11;	// Read 131 to R3
            M2.M2_MEM.memory[4] = 131;
            M2.M2_MEM.memory[5] = 8'b0101_00_01;	// Read 128 to R1
            M2.M2_MEM.memory[6] = 128;
            M2.M2_MEM.memory[7] = 8'b0101_00_00;	// Read 129 to R0
            M2.M2_MEM.memory[8] = 129;
            M2.M2_MEM.memory[9] = 8'b0010_00_01;	// Sub R1-R0 to R1
            M2.M2_MEM.memory[10] = 8'b1000_00_00;	// BRZ
            M2.M2_MEM.memory[11] = 134;		// Holds address for BRZ
            M2.M2_MEM.memory[12] = 8'b0001_10_11;	// Add R2+R3 to R3
            M2.M2_MEM.memory[13] = 8'b0111_00_11;	// BR
            M2.M2_MEM.memory[14] = 140; 
            
            // Load Data
            M2.M2_MEM.memory[128] = 6;
            M2.M2_MEM.memory[129] = 1;
            M2.M2_MEM.memory[130] = 2;
            M2.M2_MEM.memory[131] = 0;
            M2.M2_MEM.memory[134] = 139;
            M2.M2_MEM.memory[139] = 8'b1111_00_00;	//HALT
            M2.M2_MEM.memory[140] = 9;
           end        
endmodule


module Clock_Unit (output reg clock);
       parameter delay = 0;
       parameter half_cycle = 10;
       initial begin #delay clock=0; forever #half_cycle clock = ~clock; end
endmodule

/*
module tb_RISC_SPM;
        //reg reset, clk;
        //reg ;
        //wire ;

        //RISC_SPM module1();
        initial begin
               $dumpfile("tb_RISC_SPM.vcd");
               $dumpvars(0, tb_RISC_SPM);
               #100 $finish;
        end

endmodule
*/

RISC_SPM/tb_RISC_SPM.vcd
$date
	Thu Nov 11 12:44:41 2021
$end
$version
	Icarus Verilog
$end
$timescale
	1ps
$end
$scope module tb_RISC_SPM $end
$var wire 8 ! word1 [7:0] $end
$var wire 8 " word10 [7:0] $end
$var wire 8 # word11 [7:0] $end
$var wire 8 $ word12 [7:0] $end
$var wire 8 % word128 [7:0] $end
$var wire 8 & word129 [7:0] $end
$var wire 8 ' word13 [7:0] $end
$var wire 8 ( word130 [7:0] $end
$var wire 8 ) word131 [7:0] $end
$var wire 8 * word132 [7:0] $end
$var wire 8 + word133 [7:0] $end
$var wire 8 , word134 [7:0] $end
$var wire 8 - word135 [7:0] $end
$var wire 8 . word136 [7:0] $end
$var wire 8 / word137 [7:0] $end
$var wire 8 0 word138 [7:0] $end
$var wire 8 1 word139 [7:0] $end
$var wire 8 2 word14 [7:0] $end
$var wire 8 3 word140 [7:0] $end
$var wire 8 4 word2 [7:0] $end
$var wire 8 5 word255 [7:0] $end
$var wire 8 6 word3 [7:0] $end
$var wire 8 7 word4 [7:0] $end
$var wire 8 8 word5 [7:0] $end
$var wire 8 9 word6 [7:0] $end
$var wire 8 : word7 [7:0] $end
$var wire 8 ; word8 [7:0] $end
$var wire 8 < word9 [7:0] $end
$var wire 1 = word0 $end
$var wire 1 > clk $end
$var reg 9 ? k [8:0] $end
$var reg 1 @ rst $end
$scope module M1 $end
$var reg 1 > clock $end
$upscope $end
$scope module M2 $end
$var wire 2 A Sel_bus_2_mux [1:0] $end
$var wire 1 > clk $end
$var wire 1 @ rst $end
$var wire 1 B zero $end
$var wire 1 C write $end
$var wire 3 D sel_bus_1_mux [2:0] $end
$var wire 8 E mem_word [7:0] $end
$var wire 1 F load_add_R $end
$var wire 1 G load_Reg_Z $end
$var wire 1 H load_Reg_Y $end
$var wire 1 I load_R3 $end
$var wire 1 J load_R2 $end
$var wire 1 K load_R1 $end
$var wire 1 L load_R0 $end
$var wire 1 M load_PC $end
$var wire 1 N load_IR $end
$var wire 8 O instruction [7:0] $end
$var wire 1 P inc_PC $end
$var wire 8 Q bus_1 [7:0] $end
$var wire 8 R address [7:0] $end
$scope module M0_Processor $end
$var wire 1 > clk $end
$var wire 1 S inc_pc $end
$var wire 1 T load_pc $end
$var wire 1 @ rst $end
$var wire 2 U sel_bus_2_mux [1:0] $end
$var wire 1 B zflag $end
$var wire 3 V sel_bus_1_mux [2:0] $end
$var wire 4 W opcode [3:0] $end
$var wire 8 X mem_word [7:0] $end
$var wire 1 F load_add_R $end
$var wire 1 G load_Reg_Z $end
$var wire 1 H load_Reg_Y $end
$var wire 1 I load_R3 $end
$var wire 1 J load_R2 $end
$var wire 1 K load_R1 $end
$var wire 1 L load_R0 $end
$var wire 1 M load_PC $end
$var wire 1 N load_IR $end
$var wire 8 Y instruction [7:0] $end
$var wire 1 P inc_PC $end
$var wire 8 Z bus_2 [7:0] $end
$var wire 8 [ bus_1 [7:0] $end
$var wire 1 \ alu_zero_flag $end
$var wire 8 ] alu_out [7:0] $end
$var wire 8 ^ address [7:0] $end
$var wire 8 _ Y_value [7:0] $end
$var wire 8 ` R3_out [7:0] $end
$var wire 8 a R2_out [7:0] $end
$var wire 8 b R1_out [7:0] $end
$var wire 8 c R0_out [7:0] $end
$var wire 8 d PC_count [7:0] $end
$scope module ALU $end
$var wire 4 e sel [3:0] $end
$var wire 8 f data_2 [7:0] $end
$var wire 8 g data_1 [7:0] $end
$var wire 1 \ alu_zero_flag $end
$var reg 8 h alu_out [7:0] $end
$upscope $end
$scope module Add_R $end
$var wire 1 > clk $end
$var wire 1 @ rst $end
$var wire 1 F load $end
$var wire 8 i data_in [7:0] $end
$var reg 8 j data_out [7:0] $end
$upscope $end
$scope module IR $end
$var wire 1 > clk $end
$var wire 1 @ rst $end
$var wire 1 N load $end
$var wire 8 k data_in [7:0] $end
$var reg 8 l data_out [7:0] $end
$upscope $end
$scope module Mux_1 $end
$var wire 3 m sel [2:0] $end
$var wire 8 n mux_out [7:0] $end
$var wire 8 o data_e [7:0] $end
$var wire 8 p data_d [7:0] $end
$var wire 8 q data_c [7:0] $end
$var wire 8 r data_b [7:0] $end
$var wire 8 s data_a [7:0] $end
$upscope $end
$scope module Mux_2 $end
$var wire 8 t data_a [7:0] $end
$var wire 8 u data_b [7:0] $end
$var wire 2 v sel [1:0] $end
$var wire 8 w mux_out [7:0] $end
$var wire 8 x data_c [7:0] $end
$upscope $end
$scope module PC $end
$var wire 1 > clk $end
$var wire 8 y data_in [7:0] $end
$var wire 1 S inc_PC $end
$var wire 1 T load_PC $end
$var wire 1 @ rst $end
$var reg 8 z count [7:0] $end
$upscope $end
$scope module R0 $end
$var wire 1 > clk $end
$var wire 8 { data_in [7:0] $end
$var wire 1 @ rst $end
$var wire 1 L load $end
$var reg 8 | data_out [7:0] $end
$upscope $end
$scope module R1 $end
$var wire 1 > clk $end
$var wire 8 } data_in [7:0] $end
$var wire 1 @ rst $end
$var wire 1 K load $end
$var reg 8 ~ data_out [7:0] $end
$upscope $end
$scope module R2 $end
$var wire 1 > clk $end
$var wire 8 !" data_in [7:0] $end
$var wire 1 @ rst $end
$var wire 1 J load $end
$var reg 8 "" data_out [7:0] $end
$upscope $end
$scope module R3 $end
$var wire 1 > clk $end
$var wire 8 #" data_in [7:0] $end
$var wire 1 @ rst $end
$var wire 1 I load $end
$var reg 8 $" data_out [7:0] $end
$upscope $end
$scope module Reg_Y $end
$var wire 1 > clk $end
$var wire 8 %" data_in [7:0] $end
$var wire 1 @ rst $end
$var wire 1 H load $end
$var reg 8 &" data_out [7:0] $end
$upscope $end
$scope module Reg_Z $end
$var wire 1 > clk $end
$var wire 1 \ data_in $end
$var wire 1 @ rst $end
$var wire 1 G load $end
$var reg 1 B data_out $end
$upscope $end
$upscope $end
$scope module M1_Controller $end
$var wire 1 > clk $end
$var wire 8 '" instruction [7:0] $end
$var wire 1 @ rst $end
$var wire 2 (" sel_bus_2_mux [1:0] $end
$var wire 1 B zero $end
$var wire 2 )" src [1:0] $end
$var wire 3 *" sel_bus_1_mux [2:0] $end
$var wire 4 +" opcode [3:0] $end
$var wire 2 ," dest [1:0] $end
$var reg 1 -" err_flag $end
$var reg 1 P inc_PC $end
$var reg 1 N load_IR $end
$var reg 1 M load_PC $end
$var reg 1 L load_R0 $end
$var reg 1 K load_R1 $end
$var reg 1 J load_R2 $end
$var reg 1 I load_R3 $end
$var reg 1 H load_Reg_Y $end
$var reg 1 G load_Reg_Z $end
$var reg 1 F load_add_R $end
$var reg 4 ." next_state [3:0] $end
$var reg 1 /" sel_ALU $end
$var reg 1 0" sel_PC $end
$var reg 1 1" sel_R0 $end
$var reg 1 2" sel_R1 $end
$var reg 1 3" sel_R2 $end
$var reg 1 4" sel_R3 $end
$var reg 1 5" sel_bus_1 $end
$var reg 1 6" sel_mem $end
$var reg 4 7" state [3:0] $end
$var reg 1 C write $end
$scope begin output_and_next_state $end
$upscope $end
$scope begin state_transitions $end
$upscope $end
$upscope $end
$scope module M2_MEM $end
$var wire 8 8" address [7:0] $end
$var wire 1 > clk $end
$var wire 8 9" data_in [7:0] $end
$var wire 8 :" data_out [7:0] $end
$var wire 1 C write $end
$upscope $end
$upscope $end
$scope begin Flush_Memory $end
$upscope $end
$scope begin Load_program $end
$upscope $end
$upscope $end
$enddefinitions $end
#0
$dumpvars
bx :"
bx 9"
bx 8"
bx 7"
x6"
x5"
x4"
x3"
x2"
x1"
x0"
x/"
bx ."
x-"
bx ,"
bx +"
bx *"
bx )"
bz ("
bx '"
bx &"
bx %"
bx $"
bx #"
bx ""
bx !"
bx ~
bx }
bx |
bx {
bx z
bx y
bx x
bx w
bz v
bx u
bx t
bx s
bx r
bx q
bx p
bx o
bx n
bx m
bx l
bx k
bx j
bx i
bx h
bx g
bx f
bx e
bx d
bx c
bx b
bx a
bx `
bx _
bx ^
bx ]
x\
bx [
bx Z
bx Y
bx X
bx W
bx V
bz U
zT
zS
bx R
bx Q
xP
bx O
xN
xM
xL
xK
xJ
xI
xH
xG
xF
bx E
bx D
xC
xB
bz A
x@
bx ?
0>
x=
bx <
bx ;
bx :
bx 9
bx 8
bx 7
bx 6
bx 5
bx 4
bx 3
bx 2
bx 1
bx 0
bx /
bx .
bx -
bx ,
bx +
bx *
bx )
bx (
bx '
bx &
bx %
bx $
bx #
bx "
bx !
$end
#2000
1\
b0 ]
b0 h
b0 t
b1 ."
0-"
0C
06"
0/"
05"
0P
0G
0H
0F
0N
0M
0I
0J
0K
0L
00"
04"
03"
02"
01"
b0 +"
b0 )"
b0 ,"
b0 W
b0 e
b0 7"
b0 c
b0 s
b0 |
b0 b
b0 r
b0 ~
b0 a
b0 q
b0 ""
b0 `
b0 p
b0 $"
b0 _
b0 g
b0 &"
0B
b0 E
b0 X
b0 x
b0 :"
b0 R
b0 ^
b0 j
b0 8"
b0 O
b0 Y
b0 l
b0 '"
b0 d
b0 o
b0 z
0=
b0 5
b0 3
b0 1
b0 0
b0 /
b0 .
b0 -
b0 ,
b0 +
b0 *
b0 )
b0 (
b0 &
b0 %
b0 2
b0 '
b0 $
b0 #
b0 "
b0 <
b0 ;
b0 :
b0 9
b0 8
b0 7
b0 6
b0 4
b0 !
b100000000 ?
0@
#5000
b1001 3
b11110000 1
b10001011 ,
b10 (
b1 &
b110 %
b10001100 2
b1110011 '
b11011 $
b10000110 #
b10000000 "
b100001 <
b10000001 ;
b1010000 :
b10000000 9
b1010001 8
b10000011 7
b1010011 6
b10000010 4
b1010010 !
#10000
1>
#12000
1@
#20000
0>
#30000
b0 Q
b0 [
b0 f
b0 n
b0 u
b0 9"
b100 D
b100 V
b100 m
b100 *"
1F
15"
10"
b10 ."
b1 7"
1>
#40000
0>
#50000
bx Q
bx [
bx f
bx n
bx u
bx 9"
bx D
bx V
bx m
bx *"
1P
1N
16"
b11 ."
05"
0F
00"
b10 7"
bx E
bx X
bx x
bx :"
bx R
bx ^
bx j
bx 8"
1>
#60000
0>
#70000
b1011 ."
06"
0P
0N
bx +"
bx )"
bx ,"
bx W
bx e
b11 7"
bx O
bx Y
bx l
bx '"
1>
#80000
0>
#90000
b1011 7"
1>
